<?xml version="1.0" encoding="UTF-8"?>
<tv generator-info-name="WebGrab+Plus/w MDB &amp; REX Postprocess -- version  V2.1 -- Jan van Straaten" generator-info-url="http://www.webgrabplus.com">
  <channel id="Telecine Action [Brazil]">
    <display-name lang="pt">Telecine Action [Brazil]</display-name>
    <url>http://www.meuguia.tv</url>
  </channel>
  <channel id="Telecine Fun [Brazil]">
    <display-name lang="pt">Telecine Fun [Brazil]</display-name>
    <url>http://www.meuguia.tv</url>
  </channel>
  <channel id="Telecine Pipoca [Brazil]">
    <display-name lang="pt">Telecine Pipoca [Brazil]</display-name>
    <url>http://www.meuguia.tv</url>
  </channel>
  <channel id="Telecine Premium [Brazil]">
    <display-name lang="pt">Telecine Premium [Brazil]</display-name>
    <url>http://www.meuguia.tv</url>
  </channel>
  <channel id="SPACE [Brazil]">
    <display-name lang="pt">SPACE [Brazil]</display-name>
    <url>http://www.meuguia.tv</url>
  </channel>
  <channel id="TNT [Brazil]">
    <display-name lang="pt">TNT [Brazil]</display-name>
    <url>http://www.meuguia.tv</url>
  </channel>
  <channel id="Nickelodeon [Brazil]">
    <display-name lang="pt">Nickelodeon [Brazil]</display-name>
    <url>http://www.meuguia.tv</url>
  </channel>
  <channel id="Cartoon Network [Brazil]">
    <display-name lang="pt">Cartoon Network [Brazil]</display-name>
    <url>http://www.meuguia.tv</url>
  </channel>
  <channel id="Animal Planet [Brazil]">
    <display-name lang="pt">Animal Planet [Brazil]</display-name>
    <url>http://www.meuguia.tv</url>
  </channel>
  <channel id="Disney Channel HD [Brazil]">
    <display-name lang="pt">Disney Channel HD [Brazil]</display-name>
    <url>http://www.meuguia.tv</url>
  </channel>
</tv>